freeapihub/__init__.py
freeapihub-1.0.1.dist-info/LICENSE
freeapihub-1.0.1.dist-info/METADATA
freeapihub-1.0.1.dist-info/WHEEL
freeapihub-1.0.1.dist-info/top_level.txt
freeapihub-1.0.1.dist-info/RECORD
