Metadata-Version: 2.2
Name: freeapihub
Version: 1.0.1
Summary: A Python SDK for FreeApiHub, providing simple access to free APIs with support for data retrieval and integration.
Author-email: Rehan <rehanalire52@email.com>
License: Apache-2.0
Project-URL: Documentation, https://freeapi-hub.vercel.app/docs
Project-URL: Homepage, https://github.com/rehan-adi/freeapihub-python-sdk
Project-URL: Repository, https://github.com/rehan-adi/freeapihub-python-sdk
Keywords: api,sdk,freeapihub,data-retrieval,python-sdk
Classifier: Development Status :: 5 - Production/Stable
Classifier: Intended Audience :: Developers
Classifier: License :: OSI Approved :: Apache Software License
Classifier: Programming Language :: Python
Classifier: Programming Language :: Python :: 3
Classifier: Programming Language :: Python :: 3.7
Classifier: Programming Language :: Python :: 3.8
Classifier: Programming Language :: Python :: 3.9
Classifier: Programming Language :: Python :: 3.10
Classifier: Programming Language :: Python :: 3.11
Classifier: Programming Language :: Python :: 3 :: Only
Classifier: Topic :: Software Development :: Libraries
Requires-Python: >=3.7
License-File: LICENSE
Requires-Dist: httpx
Requires-Dist: python-dotenv
